{
"data": [
{"player1": "D. Medvedev", "player2": "N. Kyrgios", "highlight": "https://www.youtube.com/watch?v=i__xC6I8w54", "extendedHighlight": "https://www.youtube.com/watch?v=71epLB7jIko", "fullMatch": ""}, 
{"player1": "P. Carreno Busta", "player2": "K. Khachanov", "highlight": "https://www.youtube.com/watch?v=hHbjlwTBKTQ", "extendedHighlight": "", "fullMatch": ""}, 
{"player1": "A. Davidovich Fokina", "player2": "M. Berrettini", "highlight": "https://www.youtube.com/watch?v=1WaZ-g01Z7s", "extendedHighlight": "https://www.youtube.com/watch?v=44f5nhYWLLQ", "fullMatch": ""}, 
{"player1": "C. Moutet", "player2": "C. Ruud", "highlight": "https://www.youtube.com/watch?v=YExb6p0_I1U", "extendedHighlight": "", "fullMatch": ""}, 
{"player1": "I. Ivashka", "player2": "J. Sinner", "highlight": "https://www.youtube.com/watch?v=DdbVlsZ-KFw", "extendedHighlight": "", "fullMatch": ""}, 
{"player1": "M. Cilic", "player2": "C. Alcaraz", "highlight": "https://www.youtube.com/watch?v=YuM1DTqcCWA", "extendedHighlight": "", "fullMatch": ""}, 
{"player1": "C. Norrie", "player2": "A. Rublev", "highlight": "https://www.youtube.com/watch?v=WAMyp9whrls", "extendedHighlight": "", "fullMatch": ""}, 
{"player1": "F. Tiafoe", "player2": "R. Nadal", "highlight": "https://www.youtube.com/watch?v=IMAJJS3UFCc", "extendedHighlight": "https://www.youtube.com/watch?v=DHYjbeffHDo", "fullMatch": ""}
]
}